[{"id":1,"userName":"Tommie","dateJoined":"July 2017","profilePic":"https://rpt26-ingenuity.s3-us-west-1.amazonaws.com/reviews/618.jpg","reviewDescription":"Veritatis blanditiis aut repudiandae repudiandae temporibus at.","reviewRating":{"cleanliness":4,"communication":4,"checkIn":4,"accuracy":4,"location":5,"value":4},"listingID":1},{"id":2,"userName":"Giuseppe","dateJoined":"July 2015","profilePic":"https://rpt26-ingenuity.s3-us-west-1.amazonaws.com/reviews/38.jpg","reviewDescription":"Quisquam numquam delectus nostrum et at officiis.","reviewRating":{"cleanliness":5,"communication":4,"checkIn":4,"accuracy":5,"location":5,"value":4},"listingID":1},{"id":3,"userName":"Jaylon","dateJoined":"July 2011","profilePic":"https://rpt26-ingenuity.s3-us-west-1.amazonaws.com/reviews/744.jpg","reviewDescription":"Perferendis est et natus ex asperiores dolorem.","reviewRating":{"cleanliness":5,"communication":4,"checkIn":5,"accuracy":5,"location":4,"value":4},"listingID":1},{"id":4,"userName":"Emmitt","dateJoined":"March 2021","profilePic":"https://rpt26-ingenuity.s3-us-west-1.amazonaws.com/reviews/686.jpg","reviewDescription":"Doloremque magni molestias aut consequatur optio.","reviewRating":{"cleanliness":5,"communication":5,"checkIn":4,"accuracy":5,"location":4,"value":5},"listingID":1}]